Curve_Removal/MIS_curves.py
Curve_Removal/__init__.py
mis_curves-0.1.4.dist-info/licenses/LICENSE.txt
mis_curves-0.1.4.dist-info/METADATA
mis_curves-0.1.4.dist-info/WHEEL
mis_curves-0.1.4.dist-info/top_level.txt
mis_curves-0.1.4.dist-info/RECORD
