Metadata-Version: 2.4
Name: MIS_curves
Version: 0.1.4
Summary: Removal of too close curves in the GH/Rhino environment
Author-email: Niclas Brandt <niclasbrandt97@gmail.com>
Classifier: Programming Language :: Python :: 3
Classifier: License :: OSI Approved :: MIT License
Classifier: Operating System :: OS Independent
Requires-Python: >=3.7
License-File: LICENSE.txt
Dynamic: license-file
